snavro/__init__.py
snavro/_version.py
snavro/cli.py
snavro/reader.py
snavro-0.1.9.dist-info/licenses/LICENSE
snavro-0.1.9.dist-info/METADATA
snavro-0.1.9.dist-info/WHEEL
snavro-0.1.9.dist-info/entry_points.txt
snavro-0.1.9.dist-info/top_level.txt
snavro-0.1.9.dist-info/RECORD
